yorgassistant/__init__.py
yorgassistant/core/__init__.py
yorgassistant/core/common_models.py
yorgassistant/core/agents/__init__.py
yorgassistant/core/agents/base_agent.py
yorgassistant/core/agents/data_analysis/__init__.py
yorgassistant/core/agents/data_analysis/data_analysis.py
yorgassistant/core/agents/data_analysis/data_analysis_prompt.py
yorgassistant/core/agents/data_analysis/planner_prompt.py
yorgassistant/core/agents/data_scientist/__init__.py
yorgassistant/core/agents/data_scientist/data_scientist.py
yorgassistant/core/agents/data_scientist/data_scientist_prompt.py
yorgassistant/core/agents/software_engineer/__init__.py
yorgassistant/core/agents/software_engineer/repo_manager.py
yorgassistant/core/agents/software_engineer/software_engineer.py
yorgassistant/core/agents/software_engineer/software_engineer_prompt.py
yorgassistant/core/assistant/__init__.py
yorgassistant/core/assistant/assistant.py
yorgassistant/core/assistant/async_threads.py
yorgassistant/core/assistant/config.py
yorgassistant/core/assistant/threads.py
yorgassistant/core/assistant/prompt/__init__.py
yorgassistant/core/assistant/prompt/few_shot_cot_tools_choose_prompt.py
yorgassistant/core/assistant/prompt/few_shot_extract_parametes_from_input.py
yorgassistant/core/assistant/prompt/few_shot_response_prompt.py
yorgassistant/core/assistant/prompt/few_shot_tools_choose_prompt.py
yorgassistant/core/assistant/prompt/parameters_generate_prompt.py
yorgassistant/core/assistant/prompt/response_generate_prompt.py
yorgassistant/core/assistant/tools/__init__.py
yorgassistant/core/assistant/tools/da_tool_entity.py
yorgassistant/core/assistant/tools/da_tool_entity.yaml
yorgassistant/core/assistant/tools/example_stateful_tool.yaml
yorgassistant/core/assistant/tools/example_stateful_tool_entity.py
yorgassistant/core/assistant/tools/model.py
yorgassistant/core/assistant/tools/stateful_tool_entity.py
yorgassistant/core/assistant/tools/swe_tool.yaml
yorgassistant/core/assistant/tools/swe_tool_entity.py
yorgassistant-0.0.21.dist-info/LICENSE
yorgassistant-0.0.21.dist-info/METADATA
yorgassistant-0.0.21.dist-info/WHEEL
yorgassistant-0.0.21.dist-info/top_level.txt
yorgassistant-0.0.21.dist-info/RECORD
